MANIFEST.in
readme.md
setup.py
./assign/__init__.py
./assign/magic.py
./assign/patch.py
./assign/transformer.py
assign.egg-info/PKG-INFO
assign.egg-info/SOURCES.txt
assign.egg-info/dependency_links.txt
assign.egg-info/top_level.txt