Metadata-Version: 1.1
Name: assign
Version: 1.0.1
Summary: A Black Magic for support obj.__assign__ method
Home-page: UNKNOWN
Author: ryankung
Author-email: ryankung@ieee.org
License: MIT
Platform: any
Classifier: Intended Audience :: Developers
Classifier: Programming Language :: Python
Classifier: Topic :: Software Development :: Libraries :: Python Modules
